demonstration/__init__.py
demonstration-0.2.0.dist-info/LICENSE
demonstration-0.2.0.dist-info/WHEEL
demonstration-0.2.0.dist-info/METADATA
demonstration-0.2.0.dist-info/RECORD
